graphql_subscriptions/__init__.py
graphql_subscriptions/mock_server.py
graphql_subscriptions/subscription_manager.py
graphql_subscriptions/subscription_transport_ws.py
graphql_subscriptions/utils.py
graphql_subscriptions/validation.py
graphql_subscriptions-0.1.9.dist-info/DESCRIPTION.rst
graphql_subscriptions-0.1.9.dist-info/METADATA
graphql_subscriptions-0.1.9.dist-info/RECORD
graphql_subscriptions-0.1.9.dist-info/WHEEL
graphql_subscriptions-0.1.9.dist-info/metadata.json
graphql_subscriptions-0.1.9.dist-info/top_level.txt
