Metadata-Version: 1.1
Name: graphql-subscriptions
Version: 0.1.9
Summary: A port of apollo-graphql subscriptions for python, using                 gevent websockets, promises, and redis
Home-page: https://github.com/hballard/graphql-python-subscriptions
Author: Heath Ballard
Author-email: heath.ballard@gmail.com
License: MIT
Keywords: graphql websockets concurrent subscriptions
Platform: UNKNOWN
Classifier: Development Status :: 3 - Alpha
Classifier: Intended Audience :: Developers
Classifier: Topic :: Software Development :: Libraries
Classifier: Environment :: Web Environment
Classifier: Programming Language :: Python :: 2
Classifier: Programming Language :: Python :: 2.7
Classifier: Programming Language :: Python :: 3
Classifier: Programming Language :: Python :: 3.4
Classifier: Programming Language :: Python :: 3.5
Classifier: Programming Language :: Python :: 3.6
Classifier: License :: OSI Approved :: MIT License
